httpdriver/__about__.py
httpdriver/__init__.py
httpdriver/actions.py
httpdriver/cli.py
httpdriver/driver.py
rtsf_http-2.1.6.dist-info/LICENSE
rtsf_http-2.1.6.dist-info/METADATA
rtsf_http-2.1.6.dist-info/WHEEL
rtsf_http-2.1.6.dist-info/entry_points.txt
rtsf_http-2.1.6.dist-info/top_level.txt
rtsf_http-2.1.6.dist-info/RECORD
