Metadata-Version: 2.1
Name: rtsf-http
Version: 2.1.6
Summary: only for http(s) test, base on rtsf
Home-page: https://github.com/RockFeng0/rtsf-http
Author: 罗科峰
Author-email: lkf20031988@163.com
License: MIT
Keywords: test http api https
Platform: UNKNOWN
Requires-Python: >=2.7, !=3.0.*, !=3.1.*, !=3.2.*, !=3.3.*, <4
Requires-Dist: requests
Requires-Dist: rtsf
